abatchtaskpool/__init__.py
abatchtaskpool/async_batch_engine.py
test/__init__.py
test/test_async_batch_engine.py
abatchtaskpool-0.1.0.dist-info/METADATA
abatchtaskpool-0.1.0.dist-info/WHEEL
abatchtaskpool-0.1.0.dist-info/top_level.txt
abatchtaskpool-0.1.0.dist-info/RECORD
