Metadata-Version: 2.1
Name: abatchtaskpool
Version: 0.1.0
Summary: Python batch task pool with asyncio support
Home-page: https://github.com/weedge/abatchtaskpool
Author: weedge
Author-email: weege007@gmail.com
License: BSD 3-Clause
Project-URL: Changes, https://github.com/weedge/abatchtaskpool/releases
Project-URL: Code, https://github.com/weedge/abatchtaskpool
Project-URL: Issue tracker, https://github.com/weedge/abatchtaskpool/issues
Keywords: batch,task,pool,asyncio
Requires-Python: >=3.10
